analysis_engine/__init__.py
analysis_engine/ar_data.py
analysis_engine/benefits.py
analysis_engine/cdg_data.py
analysis_engine/cleaning.py
analysis_engine/colouring.py
analysis_engine/core_data.py
analysis_engine/costs.py
analysis_engine/dandelion.py
analysis_engine/dashboards.py
analysis_engine/data.py
analysis_engine/data_review.py
analysis_engine/dca.py
analysis_engine/dictionaries.py
analysis_engine/error_msgs.py
analysis_engine/gmpp_int.py
analysis_engine/main.py
analysis_engine/merge.py
analysis_engine/milestones.py
analysis_engine/query.py
analysis_engine/render_utils.py
analysis_engine/resourcing.py
analysis_engine/risks.py
analysis_engine/segmentation.py
analysis_engine/settings.py
analysis_engine/speed_dials.py
analysis_engine/summaries.py
analysis_engine/top35_data.py
analysis_engine-2.0.14.dist-info/LICENSE
analysis_engine-2.0.14.dist-info/METADATA
analysis_engine-2.0.14.dist-info/WHEEL
analysis_engine-2.0.14.dist-info/entry_points.txt
analysis_engine-2.0.14.dist-info/top_level.txt
analysis_engine-2.0.14.dist-info/RECORD
