Metadata-Version: 2.1
Name: analysis-engine
Version: 2.0.14
Summary: Analysis for the UK Department for Transport's major projects portfolio
Home-page: https://github.com/banillie/analysis_engine
Author: Will Grant
Author-email: will.granty@yahoo.co.uk
Classifier: Programming Language :: Python :: 3
Classifier: License :: OSI Approved :: MIT License
Classifier: Operating System :: OS Independent
Requires-Python: >=3.7
License-File: LICENSE
Requires-Dist: datamaps
Requires-Dist: python-docx (==0.8.10)
Requires-Dist: openpyxl
Requires-Dist: matplotlib (==3.4.1)
Requires-Dist: pdf2image
Requires-Dist: xlrd
